mkdocs_iframe-0.1.0.dist-info/METADATA
mkdocs_iframe-0.1.0.dist-info/WHEEL
mkdocs_iframe-0.1.0.dist-info/entry_points.txt
mkdocs_iframe-0.1.0.dist-info/licenses/LICENSE
mkdocs_iframe/__init__.py
mkdocs_iframe/loggers.py
mkdocs_iframe/plugin.py
mkdocs_iframe/py.typed
mkdocs_iframe-0.1.0.dist-info/RECORD
