Metadata-Version: 2.1
Name: mkdocs-iframe
Version: 0.1.0
Summary: MkDocs plugin to integrate HTML reports into your site.
Author-Email: Josh Mayer <joshuaamayer@gmail.com>
License: ISC
Classifier: Development Status :: 4 - Beta
Classifier: Intended Audience :: Developers
Classifier: Programming Language :: Python
Classifier: Programming Language :: Python :: 3
Classifier: Programming Language :: Python :: 3 :: Only
Classifier: Programming Language :: Python :: 3.7
Classifier: Programming Language :: Python :: 3.8
Classifier: Programming Language :: Python :: 3.9
Classifier: Programming Language :: Python :: 3.10
Classifier: Programming Language :: Python :: 3.11
Classifier: Topic :: Documentation
Classifier: Topic :: Software Development
Classifier: Topic :: Software Development :: Documentation
Classifier: Topic :: Utilities
Classifier: Typing :: Typed
Project-URL: Homepage, https://josham.github.io/mkdocs-iframe
Project-URL: Documentation, https://josham.github.io/mkdocs-iframe
Project-URL: Changelog, https://josham.github.io/mkdocs-iframe/changelog
Project-URL: Repository, https://github.com/josham/mkdocs-iframe
Project-URL: Issues, https://github.com/josham/mkdocs-iframe/issues
Project-URL: Discussions, https://github.com/josham/mkdocs-iframe/discussions
Project-URL: Funding, https://github.com/sponsors/josham
Requires-Python: >=3.7
Requires-Dist: mkdocs>=1.2
